socket_cyg/__init__.py
socket_cyg/example/__init__.py
socket_cyg/example/client_example.py
socket_cyg/socket_client.py
socket_cyg/socket_server_asyncio.py
socket_cyg-1.10.0.dist-info/METADATA
socket_cyg-1.10.0.dist-info/WHEEL
socket_cyg-1.10.0.dist-info/RECORD
