Metadata-Version: 2.4
Name: socket-cyg
Version: 1.10.0
Summary: CYG socket 封装
Author: LiuWei
Author-email: 183074632@qq.com
Requires-Python: >=3.8,<=3.13
Classifier: Programming Language :: Python :: 3
Classifier: Programming Language :: Python :: 3.8
Classifier: Programming Language :: Python :: 3.9
Classifier: Programming Language :: Python :: 3.10
Classifier: Programming Language :: Python :: 3.11
Classifier: Programming Language :: Python :: 3.12
Classifier: Programming Language :: Python :: 3.13
